[
    {
        "date": 1,
        "month": 10,
        "year": 2020,
        "localityCode": "MY-JHR04",
        "source_id": 1,
        "times": [
            "2020-09-30T21:40:00.000Z",
            "2020-09-30T22:56:00.000Z",
            "2020-10-01T05:01:00.000Z",
            "2020-10-01T08:09:00.000Z",
            "2020-10-01T11:03:00.000Z",
            "2020-10-01T12:11:00.000Z"
        ],
        "updated": "2019-12-17T14:12:09.685Z"
    },
    {
        "date": 2,
        "month": 10,
        "year": 2020,
        "localityCode": "MY-JHR04",
        "source_id": 1,
        "times": [
            "2020-10-01T21:40:00.000Z",
            "2020-10-01T22:56:00.000Z",
            "2020-10-02T05:01:00.000Z",
            "2020-10-02T08:09:00.000Z",
            "2020-10-02T11:02:00.000Z",
            "2020-10-02T12:11:00.000Z"
        ],
        "updated": "2019-12-17T14:12:09.685Z"
    },
    {
        "date": 3,
        "month": 10,
        "year": 2020,
        "localityCode": "MY-JHR04",
        "source_id": 1,
        "times": [
            "2020-10-02T21:40:00.000Z",
            "2020-10-02T22:56:00.000Z",
            "2020-10-03T05:00:00.000Z",
            "2020-10-03T08:10:00.000Z",
            "2020-10-03T11:02:00.000Z",
            "2020-10-03T12:11:00.000Z"
        ],
        "updated": "2019-12-17T14:12:09.685Z"
    },
    {
        "date": 4,
        "month": 10,
        "year": 2020,
        "localityCode": "MY-JHR04",
        "source_id": 1,
        "times": [
            "2020-10-03T21:40:00.000Z",
            "2020-10-03T22:55:00.000Z",
            "2020-10-04T05:00:00.000Z",
            "2020-10-04T08:10:00.000Z",
            "2020-10-04T11:02:00.000Z",
            "2020-10-04T12:10:00.000Z"
        ],
        "updated": "2019-12-17T14:12:09.685Z"
    },
    {
        "date": 5,
        "month": 10,
        "year": 2020,
        "localityCode": "MY-JHR04",
        "source_id": 1,
        "times": [
            "2020-10-04T21:39:00.000Z",
            "2020-10-04T22:55:00.000Z",
            "2020-10-05T05:00:00.000Z",
            "2020-10-05T08:10:00.000Z",
            "2020-10-05T11:01:00.000Z",
            "2020-10-05T12:10:00.000Z"
        ],
        "updated": "2019-12-17T14:12:09.685Z"
    },
    {
        "date": 6,
        "month": 10,
        "year": 2020,
        "localityCode": "MY-JHR04",
        "source_id": 1,
        "times": [
            "2020-10-05T21:39:00.000Z",
            "2020-10-05T22:55:00.000Z",
            "2020-10-06T04:59:00.000Z",
            "2020-10-06T08:10:00.000Z",
            "2020-10-06T11:01:00.000Z",
            "2020-10-06T12:10:00.000Z"
        ],
        "updated": "2019-12-17T14:12:09.685Z"
    },
    {
        "date": 7,
        "month": 10,
        "year": 2020,
        "localityCode": "MY-JHR04",
        "source_id": 1,
        "times": [
            "2020-10-06T21:39:00.000Z",
            "2020-10-06T22:55:00.000Z",
            "2020-10-07T04:59:00.000Z",
            "2020-10-07T08:10:00.000Z",
            "2020-10-07T11:00:00.000Z",
            "2020-10-07T12:09:00.000Z"
        ],
        "updated": "2019-12-17T14:12:09.685Z"
    },
    {
        "date": 8,
        "month": 10,
        "year": 2020,
        "localityCode": "MY-JHR04",
        "source_id": 1,
        "times": [
            "2020-10-07T21:38:00.000Z",
            "2020-10-07T22:55:00.000Z",
            "2020-10-08T04:59:00.000Z",
            "2020-10-08T08:11:00.000Z",
            "2020-10-08T11:00:00.000Z",
            "2020-10-08T12:09:00.000Z"
        ],
        "updated": "2019-12-17T14:12:09.685Z"
    },
    {
        "date": 9,
        "month": 10,
        "year": 2020,
        "localityCode": "MY-JHR04",
        "source_id": 1,
        "times": [
            "2020-10-08T21:38:00.000Z",
            "2020-10-08T22:54:00.000Z",
            "2020-10-09T04:59:00.000Z",
            "2020-10-09T08:11:00.000Z",
            "2020-10-09T11:00:00.000Z",
            "2020-10-09T12:09:00.000Z"
        ],
        "updated": "2019-12-17T14:12:09.685Z"
    },
    {
        "date": 10,
        "month": 10,
        "year": 2020,
        "localityCode": "MY-JHR04",
        "source_id": 1,
        "times": [
            "2020-10-09T21:38:00.000Z",
            "2020-10-09T22:54:00.000Z",
            "2020-10-10T04:58:00.000Z",
            "2020-10-10T08:11:00.000Z",
            "2020-10-10T10:59:00.000Z",
            "2020-10-10T12:09:00.000Z"
        ],
        "updated": "2019-12-17T14:12:09.685Z"
    },
    {
        "date": 11,
        "month": 10,
        "year": 2020,
        "localityCode": "MY-JHR04",
        "source_id": 1,
        "times": [
            "2020-10-10T21:38:00.000Z",
            "2020-10-10T22:54:00.000Z",
            "2020-10-11T04:58:00.000Z",
            "2020-10-11T08:11:00.000Z",
            "2020-10-11T10:59:00.000Z",
            "2020-10-11T12:08:00.000Z"
        ],
        "updated": "2019-12-17T14:12:09.685Z"
    },
    {
        "date": 12,
        "month": 10,
        "year": 2020,
        "localityCode": "MY-JHR04",
        "source_id": 1,
        "times": [
            "2020-10-11T21:37:00.000Z",
            "2020-10-11T22:54:00.000Z",
            "2020-10-12T04:58:00.000Z",
            "2020-10-12T08:11:00.000Z",
            "2020-10-12T10:59:00.000Z",
            "2020-10-12T12:08:00.000Z"
        ],
        "updated": "2019-12-17T14:12:09.685Z"
    },
    {
        "date": 13,
        "month": 10,
        "year": 2020,
        "localityCode": "MY-JHR04",
        "source_id": 1,
        "times": [
            "2020-10-12T21:37:00.000Z",
            "2020-10-12T22:54:00.000Z",
            "2020-10-13T04:58:00.000Z",
            "2020-10-13T08:11:00.000Z",
            "2020-10-13T10:59:00.000Z",
            "2020-10-13T12:08:00.000Z"
        ],
        "updated": "2019-12-17T14:12:09.685Z"
    },
    {
        "date": 14,
        "month": 10,
        "year": 2020,
        "localityCode": "MY-JHR04",
        "source_id": 1,
        "times": [
            "2020-10-13T21:37:00.000Z",
            "2020-10-13T22:53:00.000Z",
            "2020-10-14T04:57:00.000Z",
            "2020-10-14T08:12:00.000Z",
            "2020-10-14T10:58:00.000Z",
            "2020-10-14T12:08:00.000Z"
        ],
        "updated": "2019-12-17T14:12:09.686Z"
    },
    {
        "date": 15,
        "month": 10,
        "year": 2020,
        "localityCode": "MY-JHR04",
        "source_id": 1,
        "times": [
            "2020-10-14T21:37:00.000Z",
            "2020-10-14T22:53:00.000Z",
            "2020-10-15T04:57:00.000Z",
            "2020-10-15T08:12:00.000Z",
            "2020-10-15T10:58:00.000Z",
            "2020-10-15T12:07:00.000Z"
        ],
        "updated": "2019-12-17T14:12:09.686Z"
    },
    {
        "date": 16,
        "month": 10,
        "year": 2020,
        "localityCode": "MY-JHR04",
        "source_id": 1,
        "times": [
            "2020-10-15T21:36:00.000Z",
            "2020-10-15T22:53:00.000Z",
            "2020-10-16T04:57:00.000Z",
            "2020-10-16T08:12:00.000Z",
            "2020-10-16T10:58:00.000Z",
            "2020-10-16T12:07:00.000Z"
        ],
        "updated": "2019-12-17T14:12:09.686Z"
    },
    {
        "date": 17,
        "month": 10,
        "year": 2020,
        "localityCode": "MY-JHR04",
        "source_id": 1,
        "times": [
            "2020-10-16T21:36:00.000Z",
            "2020-10-16T22:53:00.000Z",
            "2020-10-17T04:57:00.000Z",
            "2020-10-17T08:12:00.000Z",
            "2020-10-17T10:57:00.000Z",
            "2020-10-17T12:07:00.000Z"
        ],
        "updated": "2019-12-17T14:12:09.686Z"
    },
    {
        "date": 18,
        "month": 10,
        "year": 2020,
        "localityCode": "MY-JHR04",
        "source_id": 1,
        "times": [
            "2020-10-17T21:36:00.000Z",
            "2020-10-17T22:53:00.000Z",
            "2020-10-18T04:57:00.000Z",
            "2020-10-18T08:12:00.000Z",
            "2020-10-18T10:57:00.000Z",
            "2020-10-18T12:07:00.000Z"
        ],
        "updated": "2019-12-17T14:12:09.686Z"
    },
    {
        "date": 19,
        "month": 10,
        "year": 2020,
        "localityCode": "MY-JHR04",
        "source_id": 1,
        "times": [
            "2020-10-18T21:36:00.000Z",
            "2020-10-18T22:53:00.000Z",
            "2020-10-19T04:56:00.000Z",
            "2020-10-19T08:12:00.000Z",
            "2020-10-19T10:57:00.000Z",
            "2020-10-19T12:07:00.000Z"
        ],
        "updated": "2019-12-17T14:12:09.686Z"
    },
    {
        "date": 20,
        "month": 10,
        "year": 2020,
        "localityCode": "MY-JHR04",
        "source_id": 1,
        "times": [
            "2020-10-19T21:35:00.000Z",
            "2020-10-19T22:52:00.000Z",
            "2020-10-20T04:56:00.000Z",
            "2020-10-20T08:13:00.000Z",
            "2020-10-20T10:57:00.000Z",
            "2020-10-20T12:07:00.000Z"
        ],
        "updated": "2019-12-17T14:12:09.686Z"
    },
    {
        "date": 21,
        "month": 10,
        "year": 2020,
        "localityCode": "MY-JHR04",
        "source_id": 1,
        "times": [
            "2020-10-20T21:35:00.000Z",
            "2020-10-20T22:52:00.000Z",
            "2020-10-21T04:56:00.000Z",
            "2020-10-21T08:13:00.000Z",
            "2020-10-21T10:57:00.000Z",
            "2020-10-21T12:06:00.000Z"
        ],
        "updated": "2019-12-17T14:12:09.686Z"
    },
    {
        "date": 22,
        "month": 10,
        "year": 2020,
        "localityCode": "MY-JHR04",
        "source_id": 1,
        "times": [
            "2020-10-21T21:35:00.000Z",
            "2020-10-21T22:52:00.000Z",
            "2020-10-22T04:56:00.000Z",
            "2020-10-22T08:13:00.000Z",
            "2020-10-22T10:56:00.000Z",
            "2020-10-22T12:06:00.000Z"
        ],
        "updated": "2019-12-17T14:12:09.686Z"
    },
    {
        "date": 23,
        "month": 10,
        "year": 2020,
        "localityCode": "MY-JHR04",
        "source_id": 1,
        "times": [
            "2020-10-22T21:35:00.000Z",
            "2020-10-22T22:52:00.000Z",
            "2020-10-23T04:56:00.000Z",
            "2020-10-23T08:13:00.000Z",
            "2020-10-23T10:56:00.000Z",
            "2020-10-23T12:06:00.000Z"
        ],
        "updated": "2019-12-17T14:12:09.686Z"
    },
    {
        "date": 24,
        "month": 10,
        "year": 2020,
        "localityCode": "MY-JHR04",
        "source_id": 1,
        "times": [
            "2020-10-23T21:35:00.000Z",
            "2020-10-23T22:52:00.000Z",
            "2020-10-24T04:56:00.000Z",
            "2020-10-24T08:13:00.000Z",
            "2020-10-24T10:56:00.000Z",
            "2020-10-24T12:06:00.000Z"
        ],
        "updated": "2019-12-17T14:12:09.686Z"
    },
    {
        "date": 25,
        "month": 10,
        "year": 2020,
        "localityCode": "MY-JHR04",
        "source_id": 1,
        "times": [
            "2020-10-24T21:35:00.000Z",
            "2020-10-24T22:52:00.000Z",
            "2020-10-25T04:55:00.000Z",
            "2020-10-25T08:13:00.000Z",
            "2020-10-25T10:56:00.000Z",
            "2020-10-25T12:06:00.000Z"
        ],
        "updated": "2019-12-17T14:12:09.686Z"
    },
    {
        "date": 26,
        "month": 10,
        "year": 2020,
        "localityCode": "MY-JHR04",
        "source_id": 1,
        "times": [
            "2020-10-25T21:34:00.000Z",
            "2020-10-25T22:52:00.000Z",
            "2020-10-26T04:55:00.000Z",
            "2020-10-26T08:14:00.000Z",
            "2020-10-26T10:56:00.000Z",
            "2020-10-26T12:06:00.000Z"
        ],
        "updated": "2019-12-17T14:12:09.686Z"
    },
    {
        "date": 27,
        "month": 10,
        "year": 2020,
        "localityCode": "MY-JHR04",
        "source_id": 1,
        "times": [
            "2020-10-26T21:34:00.000Z",
            "2020-10-26T22:52:00.000Z",
            "2020-10-27T04:55:00.000Z",
            "2020-10-27T08:14:00.000Z",
            "2020-10-27T10:56:00.000Z",
            "2020-10-27T12:06:00.000Z"
        ],
        "updated": "2019-12-17T14:12:09.686Z"
    },
    {
        "date": 28,
        "month": 10,
        "year": 2020,
        "localityCode": "MY-JHR04",
        "source_id": 1,
        "times": [
            "2020-10-27T21:34:00.000Z",
            "2020-10-27T22:52:00.000Z",
            "2020-10-28T04:55:00.000Z",
            "2020-10-28T08:14:00.000Z",
            "2020-10-28T10:55:00.000Z",
            "2020-10-28T12:06:00.000Z"
        ],
        "updated": "2019-12-17T14:12:09.686Z"
    },
    {
        "date": 29,
        "month": 10,
        "year": 2020,
        "localityCode": "MY-JHR04",
        "source_id": 1,
        "times": [
            "2020-10-28T21:34:00.000Z",
            "2020-10-28T22:52:00.000Z",
            "2020-10-29T04:55:00.000Z",
            "2020-10-29T08:14:00.000Z",
            "2020-10-29T10:55:00.000Z",
            "2020-10-29T12:06:00.000Z"
        ],
        "updated": "2019-12-17T14:12:09.686Z"
    },
    {
        "date": 30,
        "month": 10,
        "year": 2020,
        "localityCode": "MY-JHR04",
        "source_id": 1,
        "times": [
            "2020-10-29T21:34:00.000Z",
            "2020-10-29T22:52:00.000Z",
            "2020-10-30T04:55:00.000Z",
            "2020-10-30T08:14:00.000Z",
            "2020-10-30T10:55:00.000Z",
            "2020-10-30T12:06:00.000Z"
        ],
        "updated": "2019-12-17T14:12:09.686Z"
    },
    {
        "date": 31,
        "month": 10,
        "year": 2020,
        "localityCode": "MY-JHR04",
        "source_id": 1,
        "times": [
            "2020-10-30T21:34:00.000Z",
            "2020-10-30T22:52:00.000Z",
            "2020-10-31T04:55:00.000Z",
            "2020-10-31T08:14:00.000Z",
            "2020-10-31T10:55:00.000Z",
            "2020-10-31T12:06:00.000Z"
        ],
        "updated": "2019-12-17T14:12:09.686Z"
    }
]